{
    "page" : 1,
    "total" : 8,
    "total_pages":10,
    "seccion" : "Prendas Interiores",
    "subseccion" : "Camisas", 
    "data":[

        {
            "id" : 1,
            "imagen": "/assets/img/4.prendas/camisa_1.jpg",
            "nombre_producto" : "Túnica interior 1770s - 1780s",
            "descripcion" : "Siglo XVII, elaborada de forma artesanal",
            "tallas": ["CH", "M", "G", "XG"],
            "material": "Lino", 
            "color" : ["Blanco", "Rojo", "Azul"],
            "precio" : 600
        },
        {
            "id" : 2,
            "imagen": "/assets/img/4.prendas/camisa_2.jpg",
            "nombre_producto" : "Túnica interior, siglo XVIII",
            "descripcion" : "Siglo XVII, elaborada de forma artesanal",
            "tallas": ["CH", "M", "G", "XG"],
            "material": "Lino", 
            "color" : ["Blanco", "Rojo", "Azul"],
            "precio" : 800
        },
        {
            "id" : 3,
            "imagen": "/assets/img/4.prendas/camisa_3.jpg",
            "nombre_producto" : "Túnica romana, siglo XII",
            "descripcion" : "Siglo XVII, elaborada de forma artesanal",
            "tallas": ["CH", "M", "G", "XG"],
            "material": "Lino", 
            "color" : ["Naranja", "Rojo", "Azul"],
            "precio" : 800
        },
        {
            "id" : 4,
            "imagen": "/assets/img/4.prendas/camisa_4.jpg",
            "nombre_producto" : "Túnica, 1440s-1480s",
            "descripcion" : "Siglo XVII, elaborada de forma artesanal",
            "tallas": ["CH", "M", "G", "XG"],
            "material": "Lino", 
            "color" : ["Negro", "Rojo", "Azul"],
            "precio" : 900
        },
        {
            "id" : 5,
            "imagen": "/assets/img/4.prendas/camisa_5.png",
            "nombre_producto" : "Tunica Siglo XV",
            "descripcion" : "Siglo XVII, elaborada de forma artesanal",
            "tallas": ["CH", "M", "G", "XG"],
            "material": "Lino", 
            "color" : ["Negro", "Rojo", "Azul"],
            "precio" : 1500
        },
        {
            "id" : 6,
            "imagen": "/assets/img/4.prendas/camisa_6.jpg",
            "nombre_producto" : "Tunica Siglo XIV",
            "descripcion" : "Siglo XVII, elaborada de forma artesanal",
            "tallas": ["CH", "M", "G", "XG"],
            "material": "Lino", 
            "color" : ["Blanco", "Rojo", "Azul"],
            "precio" : 800
        },
        {
            "id" : 7,
            "imagen": "/assets/img/4.prendas/camisa_7.webp",
            "nombre_producto" : "Tunica Siglo XIII",
            "descripcion" : "Siglo XVII, elaborada de forma artesanal",
            "tallas": ["CH", "M", "G", "XG"],
            "material": "Lino", 
            "color" : ["Camello", "Rojo", "Azul"],
            "precio" : 1200
        },
        {
            "id" : 8,
            "imagen": "/assets/img/4.prendas/camisa_8.jpg",
            "nombre_producto" : "Tunica Siglo XV",
            "descripcion" : "Siglo XVII, elaborada de forma artesanal",
            "tallas": ["CH", "M", "G", "XG"],
            "material": "Lino", 
            "color" : ["Verde", "Rojo", "Azul"],
            "precio" : 800
        }
                   
    ]
}

